image_path/__init__.py
image_path/poc.py
image_path-1000.0.1.dist-info/METADATA
image_path-1000.0.1.dist-info/WHEEL
image_path-1000.0.1.dist-info/top_level.txt
image_path-1000.0.1.dist-info/RECORD
