Metadata-Version: 2.1
Name: image-path
Version: 1000.0.1
Summary: Dependecy Confusion POC
Home-page: UNKNOWN
Author: Anonymous
Author-email: kaiksi@wearehackerone.com
License: UNKNOWN
Platform: UNKNOWN
Classifier: Development Status :: 3 - Alpha
Classifier: Intended Audience :: Education
Classifier: Programming Language :: Python :: 2
Classifier: Programming Language :: Python :: 3
Classifier: Operating System :: MacOS :: MacOS X
Classifier: Operating System :: Microsoft :: Windows
Requires-Dist: requests
